tap_mongodb_z/__init__.py
tap_mongodb_z/tap.py
tap_mongodb_z/tests/__init__.py
tap_mongodb_z/tests/test_core.py
tap_mongodb_z-0.1.18.dist-info/entry_points.txt
tap_mongodb_z-0.1.18.dist-info/WHEEL
tap_mongodb_z-0.1.18.dist-info/METADATA
tap_mongodb_z-0.1.18.dist-info/RECORD
