Metadata-Version: 2.1
Name: tap-mongodb-z
Version: 0.1.18
Summary: `tap-mongodb` is a Singer tap for MongoDB, built with the Meltano SDK for Singer Taps.
License: Apache 2.0
Keywords: ELT,MongoDB
Author: Alex Butler
Author-email: butler.alex2010@gmail.com
Requires-Python: >=3.7.1,<3.11
Classifier: License :: Other/Proprietary License
Classifier: Programming Language :: Python :: 3
Classifier: Programming Language :: Python :: 3.8
Classifier: Programming Language :: Python :: 3.9
Classifier: Programming Language :: Python :: 3.10
Requires-Dist: orjson (>=3.8.2,<4.0.0)
Requires-Dist: pymongo[srv] (>=4.3.3,<5.0.0)
Requires-Dist: requests (>=2.25.1,<3.0.0)
Requires-Dist: singer-sdk (>=0.17.0,<0.18.0)
